latticeflow/__init__.py
latticeflow/info.py
latticeflow_core-0.0.1.dist-info/METADATA
latticeflow_core-0.0.1.dist-info/WHEEL
latticeflow_core-0.0.1.dist-info/top_level.txt
latticeflow_core-0.0.1.dist-info/RECORD
